mattermost_notify/__init__.py
mattermost_notify/api.py
mattermost_notify/cli.py
mattermost_notify/client.py
mattermost_notify/config.py
notify_mattermost-0.1.2.dist-info/METADATA
notify_mattermost-0.1.2.dist-info/WHEEL
notify_mattermost-0.1.2.dist-info/entry_points.txt
notify_mattermost-0.1.2.dist-info/top_level.txt
notify_mattermost-0.1.2.dist-info/RECORD
