Metadata-Version: 2.2
Name: notify-mattermost
Version: 0.1.2
Summary: A tool to send notifications to Mattermost
Home-page: https://github.com/NoahHenrikKleinschmidt/mattermost-notify
Author: Noah Kleinschmidt
Author-email: noah.kleinschmidt@unibe.ch
Requires-Dist: requests
Requires-Dist: argparse
Dynamic: author
Dynamic: author-email
Dynamic: description
Dynamic: description-content-type
Dynamic: home-page
Dynamic: requires-dist
Dynamic: summary
